{
  "info": {
    "symbol": "RELIANCE",
    "companyName": "Reliance Industries Limited",
    "industry": "Refineries & Marketing",
    "activeSeries": [
      "EQ",
      "T0"
    ],
    "debtSeries": [],
    "isFNOSec": true,
    "isCASec": false,
    "isSLBSec": true,
    "isDebtSec": false,
    "isSuspended": false,
    "tempSuspendedSeries": [],
    "isETFSec": false,
    "isDelisted": false,
    "isin": "INE002A01018",
    "slb_isin": "INE002A01018",
    "listingDate": "1995-11-29",
    "isMunicipalBond": false,
    "isHybridSymbol": false,
    "segment": "EQUITY"
  },
  "underlyingValue": "-",
  "vfq": "-",
  "fut_timestamp": "-",
  "opt_timestamp": "-",
  "stocks": [],
  "strikePrices": [],
  "expiryDates": [],
  "allSymbol": [
    "UNOMINDA",
    "EICHERMOT",
    "PNB",
    "JSWENERGY",
    "ADANIGREEN",
    "MAXHEALTH",
    "INDUSINDBK",
    "BSE",
    "CONCOR",
    "TMPV",
    "SUNPHARMA",
    "FORCEMOT",
    "NTPC",
    "WAAREEENER",
    "INDUSTOWER",
    "DELHIVERY",
    "ASHOKLEY",
    "SUPREMEIND",
    "TATAPOWER",
    "NUVAMA",
    "ICICIPRULI",
    "POLICYBZR",
    "EXIDEIND",
    "INDIGO",
    "KEI",
    "TITAN",
    "CROMPTON",
    "BAJAJ-AUTO",
    "PAGEIND",
    "CANBK",
    "BAJFINANCE",
    "GMRAIRPORT",
    "RELIANCE",
    "BANKINDIA",
    "ABB",
    "HINDPETRO",
    "TATAELXSI",
    "BDL",
    "CIPLA",
    "DIVISLAB",
    "OFSS",
    "IDFCFIRSTB",
    "NMDC",
    "TATATECH",
    "OBEROIRLTY",
    "CDSL",
    "BEL",
    "BLUESTARCO",
    "PIDILITIND",
    "DIXON",
    "HAL",
    "NYKAA",
    "VMM",
    "ITC",
    "PPLPHARMA",
    "SWIGGY",
    "LICI",
    "APLAPOLLO",
    "SBICARD",
    "ETERNAL",
    "JIOFIN",
    "MARUTI",
    "RECLTD",
    "PATANJALI",
    "WIPRO",
    "NESTLEIND",
    "BAJAJHLDNG",
    "ADANIPORTS",
    "INFY",
    "CAMS",
    "MOTHERSON",
    "BAJAJFINSV",
    "PREMIERENE",
    "ADANIENSOL",
    "KFINTECH",
    "ICICIGI",
    "TORNTPOWER",
    "HYUNDAI",
    "KALYANKJIL",
    "INDHOTEL",
    "TECHM",
    "MPHASIS",
    "SBILIFE",
    "IEX",
    "DLF",
    "FORTIS",
    "JUBLFOOD",
    "VOLTAS",
    "MUTHOOTFIN",
    "IDEA",
    "JSWSTEEL",
    "PRESTIGE",
    "ULTRACEMCO",
    "ONGC",
    "HAVELLS",
    "PETRONET",
    "BHARATFORG",
    "LICHSGFIN",
    "360ONE",
    "POWERINDIA",
    "DALBHARAT",
    "RBLBANK",
    "HDFCLIFE",
    "CGPOWER",
    "DMART",
    "HDFCAMC",
    "MOTILALOFS",
    "PGEL",
    "TATACONSUM",
    "SHRIRAMFIN",
    "SOLARINDS",
    "HINDUNILVR",
    "LAURUSLABS",
    "PNBHOUSING",
    "NHPC",
    "AUROPHARMA",
    "MANAPPURAM",
    "PFC",
    "UPL",
    "GODFRYPHLP",
    "LUPIN",
    "DABUR",
    "VBL",
    "ABCAPITAL",
    "RVNL",
    "BPCL",
    "JINDALSTEL",
    "POWERGRID",
    "NBCC",
    "HINDALCO",
    "ICICIBANK",
    "DRREDDY",
    "POLYCAB",
    "MAZDOCK",
    "NATIONALUM",
    "TRENT",
    "COALINDIA",
    "COFORGE",
    "NAUKRI",
    "MANKIND",
    "GAIL",
    "UNIONBANK",
    "VEDL",
    "KAYNES",
    "GODREJCP",
    "MARICO",
    "UNITDSPR",
    "HEROMOTOCO",
    "BHEL",
    "AMBER",
    "SONACOMS",
    "TORNTPHARM",
    "GODREJPROP",
    "SAMMAANCAP",
    "BHARTIARTL",
    "TATASTEEL",
    "MCX",
    "IRFC",
    "TIINDIA",
    "BRITANNIA",
    "PAYTM",
    "LT",
    "LODHA",
    "SUZLON",
    "GRASIM",
    "ADANIPOWER",
    "IREDA",
    "SBIN",
    "SHREECEM",
    "MFSL",
    "HUDCO",
    "ALKEM",
    "KPITTECH",
    "INDIANB",
    "SIEMENS",
    "CUMMINSIND",
    "HCLTECH",
    "ANGELONE",
    "PIIND",
    "BIOCON",
    "OIL",
    "NAM-INDIA",
    "LTF",
    "LTM",
    "TCS",
    "AMBUJACEM",
    "SRF",
    "AUBANK",
    "CHOLAFIN",
    "COLPAL",
    "HDFCBANK",
    "BANKBARODA",
    "AXISBANK",
    "SAIL",
    "ASIANPAINT",
    "TVSMOTOR",
    "IOC",
    "ADANIENT",
    "BOSCHLTD",
    "GLENMARK",
    "PERSISTENT",
    "HINDZINC",
    "PHOENIXLTD",
    "KOTAKBANK",
    "FEDERALBNK",
    "M&M",
    "BANDHANBNK",
    "COCHINSHIP",
    "APOLLOHOSP",
    "YESBANK",
    "INOXWIND",
    "ASTRAL",
    "ZYDUSLIFE"
  ],
  "underlyingInfo": {
    "marketCap": [
      {
        "avgMktCap": "1987243.61",
        "month": "July      2025",
        "avgDailyVol": "10728680"
      },
      {
        "avgMktCap": "1884525.02",
        "month": "August    2025",
        "avgDailyVol": "9955835"
      },
      {
        "avgMktCap": "1871682.44",
        "month": "September 2025",
        "avgDailyVol": "9705384"
      },
      {
        "avgMktCap": "1922977.25",
        "month": "October   2025",
        "avgDailyVol": "11859988"
      },
      {
        "avgMktCap": "2057263.47",
        "month": "November  2025",
        "avgDailyVol": "10588721"
      },
      {
        "avgMktCap": "2098142.22",
        "month": "December  2025",
        "avgDailyVol": "8344592"
      }
    ],
    "volatility": [
      {
        "maxVolatility": "1.39",
        "minVolatility": "1.21",
        "avgVolatility": "1.3"
      }
    ]
  },
  "expiryDatesByInstrument": {}
}